AutoPrep/__init__.py
AutoPrep/auto_decorators.py
AutoPrep/autoprep.py
AutoPrep/main.py
AutoPrep/pipeline_configuration.py
AutoPrep/tests.py
AutoPrep/pipelines/__init__.py
AutoPrep/pipelines/dummy/TypeInferenceTransformer.py
AutoPrep/pipelines/dummy/__init__.py
AutoPrep/pipelines/nan_handling/NaNColumnCreator.py
AutoPrep/pipelines/nan_handling/NaNColumnCreatorTotal.py
AutoPrep/pipelines/nan_handling/__init__.py
AutoPrep/pipelines/statistical/MedianAbsolutDeviation.py
AutoPrep/pipelines/statistical/MedianAbsolutDeviationTotal.py
AutoPrep/pipelines/statistical/SpearmanCheck.py
AutoPrep/pipelines/statistical/TukeyTransformer.py
AutoPrep/pipelines/statistical/TukeyTransformerTotal.py
AutoPrep/pipelines/statistical/ZTransformerMean.py
AutoPrep/pipelines/statistical/ZTransformerMeanTotal.py
AutoPrep/pipelines/statistical/__init__.py
AutoPrep/pipelines/timeseries/DateEncoder.py
AutoPrep/pipelines/timeseries/TimeSeriesImputer.py
AutoPrep/pipelines/timeseries/__init__.py
AutoPrep-3.0.0.dist-info/LICENSE
AutoPrep-3.0.0.dist-info/METADATA
AutoPrep-3.0.0.dist-info/WHEEL
AutoPrep-3.0.0.dist-info/top_level.txt
AutoPrep-3.0.0.dist-info/RECORD
