Metadata-Version: 2.1
Name: AutoPrep
Version: 3.0.0
Summary: AutoPrep is an automated preprocessing pipeline with univariate anomaly marking
Home-page: https://github.com/JAdelhelm/AutoPrepn
Author: Jörg Adelhelm
Author-email: Jörg Adelhelm <adeljoe@gmx.de>
License: MIT
Project-URL: Homepage, https://github.com/JAdelhelm/AutoPrep
Project-URL: Issues, https://github.com/JAdelhelm/AutoPrep/issues
Keywords: anomaly-detection,preprocessing,automated,automated-preprocessing,cleaning
Classifier: Development Status :: 4 - Beta
Classifier: License :: OSI Approved :: MIT License
Classifier: Operating System :: OS Independent
Classifier: Programming Language :: Python :: 3.9
Classifier: Programming Language :: Python :: 3.10
Classifier: Programming Language :: Python :: 3.11
Classifier: Programming Language :: Python :: 3.12
Requires-Python: >=3.8
License-File: LICENSE
Requires-Dist: scikit-learn
Requires-Dist: category-encoders
Requires-Dist: bitstring
Requires-Dist: pandas
Requires-Dist: numpy
